README.md
setup.py
demo/__init__.py
demo/config.py
demo/demo_kafka_producer.py
logger/__init__.py
logger/command_validator.py
logger/constant.py
logger/grep_interface.py
logger/grep_manager.py
logger/kafka_factory.py
logger/test.py
reverse_kafka_logger.egg-info/PKG-INFO
reverse_kafka_logger.egg-info/SOURCES.txt
reverse_kafka_logger.egg-info/dependency_links.txt
reverse_kafka_logger.egg-info/entry_points.txt
reverse_kafka_logger.egg-info/requires.txt
reverse_kafka_logger.egg-info/top_level.txt
tests/__init__.py
tests/logger/__init__.py
tests/logger/test_grep_manager.py