Metadata-Version: 2.1
Name: reverse-kafka-logger
Version: 0.1.2
Summary: grep kafka message reversely from the end offset to start offset
Home-page: https://github.com/edwardsujono/kafka-logger
Author: Edward Sujono
License: UNKNOWN
Platform: UNKNOWN
Classifier: Programming Language :: Python :: 2.7
Classifier: License :: OSI Approved :: MIT License
Classifier: Operating System :: OS Independent
